curve_interp/__init__.py
curve_interp/interp.py
curve_interp-1.0.dist-info/LICENSE
curve_interp-1.0.dist-info/METADATA
curve_interp-1.0.dist-info/WHEEL
curve_interp-1.0.dist-info/top_level.txt
curve_interp-1.0.dist-info/RECORD
